CHANGES.txt
DEPENDENCES.txt
README.txt
setup.py
src/ng/__init__.py
src/ng.app.smartbanner.egg-info/PKG-INFO
src/ng.app.smartbanner.egg-info/SOURCES.txt
src/ng.app.smartbanner.egg-info/dependency_links.txt
src/ng.app.smartbanner.egg-info/namespace_packages.txt
src/ng.app.smartbanner.egg-info/not-zip-safe
src/ng.app.smartbanner.egg-info/requires.txt
src/ng.app.smartbanner.egg-info/top_level.txt
src/ng/app/__init__.py
src/ng/app/smartbanner/__init__.py
src/ng/app/smartbanner/configure.zcml
src/ng/app/smartbanner/ng.app.smartbanner.txt
src/ng/app/smartbanner/etc/ng.app.smartbanner-configure.zcml
src/ng/app/smartbanner/smartbanner/__init__.py
src/ng/app/smartbanner/smartbanner/configure.zcml
src/ng/app/smartbanner/smartbanner/interfaces.py
src/ng/app/smartbanner/smartbanner/smartbanner.py
src/ng/app/smartbanner/smartbanner/smartbannerdumb.py
src/ng/app/smartbanner/smartbanner/browser/__init__.py
src/ng/app/smartbanner/smartbanner/browser/configure.zcml
src/ng/app/smartbanner/smartbanner/browser/smartbannerview.pt
src/ng/app/smartbanner/smartbanner/browser/smartbannerview.py
src/ng/app/smartbanner/smartbanner/browser/smartbannerviewdumb.pt
src/ng/app/smartbanner/smartbanneralgorithm/__init__.py
src/ng/app/smartbanner/smartbanneralgorithm/configure.zcml
src/ng/app/smartbanner/smartbanneralgorithm/interfaces.py
src/ng/app/smartbanner/smartbanneralgorithm/smartbanneralgorithm.py
src/ng/app/smartbanner/smartbanneralgorithm/smartbanneralgorithmvocabulary.py
src/ng/app/smartbanner/smartbannercontainer/__init__.py
src/ng/app/smartbanner/smartbannercontainer/configure.zcml
src/ng/app/smartbanner/smartbannercontainer/interfaces.py
src/ng/app/smartbanner/smartbannercontainer/smartbannercontainer.py
src/ng/app/smartbanner/smartbannercontainer/browser/__init__.py
src/ng/app/smartbanner/smartbannercontainer/browser/configure.zcml
src/ng/app/smartbanner/smartbannercontainernamespace/__init__.py
src/ng/app/smartbanner/smartbannercontainernamespace/configure.zcml
src/ng/app/smartbanner/smartbannercontainernamespace/smartbannercontainernamespace.py
src/ng/app/smartbanner/smartbannernamespace/__init__.py
src/ng/app/smartbanner/smartbannernamespace/configure.zcml
src/ng/app/smartbanner/smartbannernamespace/interfaces.py
src/ng/app/smartbanner/smartbannernamespace/smartbannernamespace.py
