Metadata-Version: 1.0
Name: ng.app.smartbanner
Version: 0.1.2
Summary: Simple banner system
Home-page: http://www.dreambot.ru/dreambotzope3releases/ng.app.smartbanner
Author: DreamBot Developers Team
Author-email: dbdt@dreambot.ru
License: GPL v2.1
Platform: UNKNOWN
Classifier: Environment :: Web Environment
Classifier: Intended Audience :: Developers
Classifier: License :: OSI Approved :: GNU General Public License (GPL)
Classifier: Programming Language :: Python
Classifier: Operating System :: OS Independent
Classifier: Topic :: Internet :: WWW/HTTP
Classifier: Framework :: Zope3
